gostmodels/__init__.py
gostmodels/elastic_model.py
gostmodels-0.2.4.dist-info/METADATA
gostmodels-0.2.4.dist-info/WHEEL
gostmodels-0.2.4.dist-info/top_level.txt
gostmodels-0.2.4.dist-info/RECORD
