Metadata-Version: 2.4
Name: gostmodels
Version: 0.2.4
Summary: ElasticModel: a thin Pydantic v2 BaseModel wrapper for partial/nested data with lazy access—unloaded fields raise NotLoadedFieldError.
Author-email: Steppe_Mammoth <qwqwqww505@yahoo.com>
License: MIT
Project-URL: Homepage, https://github.com/Steppe-Mammoth/GostModels
Requires-Python: >=3.10
